// compiled from: Calculator1.java

  // access flags 0x9
  public static calcAverage([I)D
***0***
   L0
    LINENUMBER 4 L0
    ICONST_0
    ISTORE 1
   L1
    LINENUMBER 5 L1
    ICONST_0
    ISTORE 2
   L2
    GOTO L3



*** Basic Block 1 ***
   L4
    LINENUMBER 6 L4
   FRAME APPEND [I I]
    ILOAD 1
    ALOAD 0
    ILOAD 2
    IALOAD
    IADD
    ISTORE 1
   L5
    LINENUMBER 5 L5
    IINC 2 1



*** Basic Block 2 ***
   L3
   FRAME SAME
    ILOAD 2
    ALOAD 0
    ARRAYLENGTH
    IF_ICMPLT L4



***3***
   L6
    LINENUMBER 8 L6
    ILOAD 1
    ALOAD 0
    ARRAYLENGTH
    IDIV
    I2D
    DRETURN
   L7
    LOCALVARIABLE array [I L0 L7 0
    LOCALVARIABLE sum I L1 L7 1
    LOCALVARIABLE i I L2 L6 2
    MAXSTACK = 3
    MAXLOCALS = 3



  // access flags 0x9
  public static main([Ljava/lang/String;)V
***0***
   L0
    LINENUMBER 12 L0
    ICONST_4
    NEWARRAY T_INT
    DUP
    ICONST_0
    ICONST_1
    IASTORE
    DUP
    ICONST_1
    ICONST_2
    IASTORE
    DUP
    ICONST_2
    ICONST_3
    IASTORE
    DUP
    ICONST_3
    ICONST_4
    IASTORE
    ASTORE 1
   L1
    LINENUMBER 13 L1
    ICONST_4
    NEWARRAY T_INT
    DUP
    ICONST_0
    BIPUSH 10
    IASTORE
    DUP
    ICONST_1
    BIPUSH 20
    IASTORE
    DUP
    ICONST_2
    BIPUSH 30
    IASTORE
    DUP
    ICONST_3
    BIPUSH 40
    IASTORE
    ASTORE 2
   L2
    LINENUMBER 14 L2
    GETSTATIC java/lang/System.out : Ljava/io/PrintStream;
    ALOAD 1
    INVOKESTATIC Calculator1.calcAverage ([I)D
    INVOKEVIRTUAL java/io/PrintStream.println (D)V
   L3
    LINENUMBER 15 L3
    GETSTATIC java/lang/System.out : Ljava/io/PrintStream;
    ALOAD 2
    INVOKESTATIC Calculator1.calcAverage ([I)D
    INVOKEVIRTUAL java/io/PrintStream.println (D)V
   L4
    LINENUMBER 16 L4
    RETURN
   L5
    LOCALVARIABLE args [Ljava/lang/String; L0 L5 0
    LOCALVARIABLE array1 [I L1 L5 1
    LOCALVARIABLE array2 [I L2 L5 2
    MAXSTACK = 4
    MAXLOCALS = 3
}
