head,L1126829932 0 25 aload 1,L1126829932 1 21 iload 6,L1126829932 2 46 iaload,L1126829932 3 21 iload 7,L1126829932 4 163 if_icmpgt L2119867878,L1153274506 0 21 iload 3,L1153274506 1 54 istore 6,L1158576396 0 25 aload 1,L1158576396 1 21 iload 5,L1158576396 2 46 iaload,L1158576396 3 21 iload 7,L1158576396 4 161 if_icmplt L689021860,L1376843475 0 167 goto L1471987900,L1471987900 0 21 iload 5,L1471987900 1 21 iload 6,L1471987900 2 164 if_icmple L1158576396,L1481625201 0 132 iinc 6,L1601866242 0 21 iload 2,L1601866242 1 21 iload 6,L1601866242 2 162 if_icmpge L1710930502,L1710930502 0 21 iload 5,L1710930502 1 21 iload 3,L1710930502 2 162 if_icmpge L1932213587,L1713890131 0 21 iload 2,L1713890131 1 54 istore 5,L1777831665 0 25 aload 1,L1777831665 1 21 iload 5,L1777831665 2 46 iaload,L1777831665 3 54 istore 8,L1865721816 0 21 iload 5,L1865721816 1 21 iload 6,L1865721816 2 163 if_icmpgt L1471987900,L1932213587 0 177 return,L1943435117 0 25 aload 1,L1943435117 1 21 iload 6,L1943435117 2 21 iload 8,L1943435117 3 79 iastore,L2044708167 0 25 aload 1,L2044708167 1 21 iload 2,L2044708167 2 21 iload 3,L2044708167 3 21 iload 2,L2044708167 4 100 isub,L2044708167 5 5 iconst_2,L2044708167 6 108 idiv,L2044708167 7 96 iadd,L2044708167 8 46 iaload,L2044708167 9 54 istore 7,L2076812944 0 25 aload 1,L2076812944 1 21 iload 5,L2076812944 2 25 aload 1,L2076812944 3 21 iload 6,L2076812944 4 46 iaload,L2076812944 5 79 iastore,L2119867878 0 132 iinc 6,L466046775 0 25 aload 0,L466046775 1 25 aload 1,L466046775 2 21 iload 5,L466046775 3 21 iload 3,L466046775 4 183 invokespecial edu/columbia/psl/cc/Sort quickSort ([III)V,L689021860 0 132 iinc 5,L802913784 0 25 aload 0,L802913784 1 25 aload 1,L802913784 2 21 iload 2,L802913784 3 21 iload 6,L802913784 4 183 invokespecial edu/columbia/psl/cc/Sort quickSort ([III)V,L87740549 0 132 iinc 5,L959260223 0 167 goto L1126829932
L1126829932 0 25 aload 1,0,100,1,100,2,100,100,100,100,100,100,100,100,100,100,100,100,100,100,100,100,100,100,100,100,100,100,100,100,3,3,3,100,4,4,4,4,100,100,100,100,100,100,100,100,100,100,4,4,4,4,4,4,3,100,100,100,100,100,100,100,100,100,100,100,4,100
L1126829932 1 21 iload 6,100,0,1,100,2,100,100,100,100,100,100,100,100,100,100,100,100,100,100,100,100,100,100,100,100,100,100,100,100,3,3,3,100,4,4,4,4,100,100,100,100,100,100,100,100,100,100,4,4,4,4,4,4,3,100,100,100,100,100,100,100,100,100,100,100,4,100
L1126829932 2 46 iaload,2,2,0,2,1,100,100,100,100,100,100,100,100,100,100,100,100,100,100,100,100,100,100,100,100,100,100,100,100,2,2,2,100,3,3,3,3,100,100,100,100,100,100,100,100,100,100,3,3,3,3,3,3,2,100,100,100,100,100,100,100,100,100,100,100,3,100
L1126829932 3 21 iload 7,2,2,2,0,1,100,100,100,100,100,100,100,100,100,100,100,100,100,100,100,100,100,100,100,100,100,100,100,100,2,2,2,100,3,3,3,3,100,100,100,100,100,100,100,100,100,100,3,3,3,3,3,3,2,100,100,100,100,100,100,100,100,100,100,100,3,100
L1126829932 4 163 if_icmpgt L2119867878,1,1,1,1,0,100,100,100,100,100,100,100,100,2,2,2,2,3,3,3,4,4,4,100,100,2,2,2,2,1,1,1,5,2,2,2,2,100,100,100,100,100,100,100,100,100,100,2,2,2,2,2,2,1,5,5,5,5,5,100,4,4,4,3,4,2,100
L1153274506 0 21 iload 3,100,2,3,5,4,0,1,100,100,100,100,100,100,6,2,3,6,4,4,4,5,5,5,100,100,6,6,6,6,5,5,5,6,6,6,6,6,100,100,100,100,100,100,100,100,100,100,6,6,6,6,6,6,5,6,6,6,6,6,100,5,5,5,5,5,6,100
L1153274506 1 54 istore 6,100,1,2,4,3,100,0,100,100,100,100,100,100,5,1,2,5,3,3,3,4,4,4,100,100,5,5,5,5,4,4,4,5,5,5,5,5,100,100,100,100,100,100,100,100,100,100,5,5,5,5,5,5,4,5,5,5,5,5,100,4,4,4,4,4,5,100
L1158576396 0 25 aload 1,100,100,100,100,100,100,100,0,100,1,100,2,100,100,100,100,100,100,100,100,100,100,100,100,100,100,100,100,100,100,100,100,100,100,100,100,100,100,100,100,100,100,100,100,100,100,100,100,100,100,100,100,100,100,100,100,100,100,100,3,100,100,100,100,100,100,3
L1158576396 1 21 iload 5,100,100,100,100,100,100,100,100,0,1,100,2,100,100,100,100,100,100,100,100,100,100,100,100,100,100,100,100,100,100,100,100,100,100,100,100,100,100,100,100,100,100,100,100,100,100,100,100,100,100,100,100,100,100,100,100,100,100,100,3,100,100,100,100,100,100,3
L1158576396 2 46 iaload,100,100,100,100,100,100,100,2,2,0,2,1,100,100,100,100,100,100,100,100,100,100,100,100,100,100,100,100,100,100,100,100,100,100,100,100,100,100,100,100,100,100,100,100,100,100,100,100,100,100,100,100,100,100,100,100,100,100,100,2,100,100,100,100,100,100,2
L1158576396 3 21 iload 7,100,100,100,100,100,100,100,2,2,2,0,1,100,100,100,100,100,100,100,100,100,100,100,100,100,100,100,100,100,100,100,100,100,100,100,100,100,100,100,100,100,100,100,100,100,100,100,100,100,100,100,100,100,100,100,100,100,100,100,2,100,100,100,100,100,100,2
L1158576396 4 161 if_icmplt L689021860,2,2,2,2,2,100,100,1,1,1,1,0,100,2,4,3,4,4,4,4,2,5,3,100,100,4,4,4,4,2,3,3,4,4,4,4,4,100,100,100,100,100,100,100,100,100,100,4,4,4,4,4,4,3,4,4,2,4,3,1,5,5,5,5,5,4,1
L1376843475 0 167 goto L1471987900,100,100,100,100,100,100,100,2,2,2,2,2,0,1,1,1,6,2,2,2,3,3,3,100,100,6,6,6,6,4,5,5,4,6,6,6,6,100,100,100,100,100,100,100,100,100,100,6,6,6,6,6,6,5,4,4,4,4,4,3,3,3,3,3,3,6,3
L1471987900 0 21 iload 5,100,100,100,100,100,100,100,2,2,2,2,2,100,0,6,1,6,2,2,2,3,3,3,100,100,6,6,6,6,4,5,5,4,6,6,6,6,100,100,100,100,100,100,100,100,100,100,6,6,6,6,6,6,5,4,4,4,4,4,3,3,3,3,3,3,6,3
L1471987900 1 21 iload 6,100,100,100,100,100,100,100,2,2,2,2,2,100,4,0,1,6,2,2,2,3,3,3,100,100,6,6,6,6,4,5,5,4,6,6,6,6,100,100,100,100,100,100,100,100,100,100,6,6,6,6,6,6,5,4,4,4,4,4,3,3,3,3,3,3,6,3
L1471987900 2 164 if_icmple L1158576396,3,3,3,3,3,100,100,1,1,1,1,1,100,3,5,0,5,1,1,1,2,2,2,100,100,5,5,5,5,3,4,4,3,5,5,5,5,100,100,100,100,100,100,100,100,100,100,5,5,5,5,5,5,4,3,3,3,3,3,2,2,2,2,2,2,5,2
L1481625201 0 132 iinc 6,100,1,2,4,3,100,100,3,3,3,3,3,100,5,1,2,0,3,1,2,3,3,3,100,100,5,5,5,5,4,1,2,4,3,1,3,2,100,100,100,100,100,100,100,100,100,100,3,3,3,1,2,3,4,4,4,4,4,4,4,3,3,3,1,2,3,4
L1601866242 0 21 iload 2,100,100,100,100,100,100,100,100,100,100,100,100,100,100,100,100,100,0,100,1,2,2,2,100,100,100,100,100,100,100,100,100,3,100,100,100,100,100,100,100,100,100,100,100,100,100,100,100,100,100,100,100,100,100,3,3,3,3,3,100,2,2,2,2,2,100,100
L1601866242 1 21 iload 6,100,100,100,100,100,100,100,100,100,100,100,100,100,100,100,100,100,100,0,1,2,2,2,100,100,100,100,100,100,100,100,100,3,100,100,100,100,100,100,100,100,100,100,100,100,100,100,100,100,100,100,100,100,100,3,3,3,3,3,100,2,2,2,2,2,100,100
L1601866242 2 162 if_icmpge L1710930502,100,100,100,100,100,100,100,100,100,100,100,100,100,100,100,100,100,100,100,0,1,1,1,100,100,100,100,100,100,100,100,100,2,100,100,100,100,100,100,100,100,100,100,100,100,100,100,100,100,100,100,100,100,100,2,2,2,2,2,100,1,1,1,1,1,100,100
L1710930502 0 21 iload 5,100,100,100,100,100,100,100,100,100,100,100,100,100,100,100,100,100,100,100,100,0,100,1,100,100,100,100,100,100,100,100,100,2,100,100,100,100,100,100,100,100,100,100,100,100,100,100,100,100,100,100,100,100,100,2,2,2,2,2,100,100,100,100,100,100,100,100
L1710930502 1 21 iload 3,100,100,100,100,100,100,100,100,100,100,100,100,100,100,100,100,100,100,100,100,100,0,1,100,100,100,100,100,100,100,100,100,2,100,100,100,100,100,100,100,100,100,100,100,100,100,100,100,100,100,100,100,100,100,2,2,2,2,2,100,100,100,100,100,100,100,100
L1710930502 2 162 if_icmpge L1932213587,100,100,100,100,100,100,100,100,100,100,100,100,100,100,100,100,100,100,100,100,100,100,0,100,100,100,100,100,100,100,100,100,1,100,100,100,100,100,100,100,100,100,100,100,100,100,100,100,100,100,100,100,100,100,1,1,1,1,1,100,100,100,100,100,100,100,100
L1713890131 0 21 iload 2,100,100,100,100,100,100,100,100,2,3,5,4,100,2,8,3,8,4,4,4,5,5,5,0,1,8,2,3,4,2,7,3,6,4,4,4,4,100,100,100,100,100,100,100,100,100,100,4,2,4,4,4,3,7,6,6,6,6,6,5,5,5,5,5,5,4,5
L1713890131 1 54 istore 5,100,100,100,100,100,100,100,3,1,2,3,3,100,1,7,2,7,3,3,3,4,4,4,100,0,7,1,2,3,1,6,2,5,3,3,3,3,100,100,100,100,100,100,100,100,100,100,3,1,3,3,3,2,6,5,5,5,5,5,4,4,4,4,4,4,3,4
L1777831665 0 25 aload 1,100,100,100,100,100,100,100,100,100,100,100,100,100,100,100,100,100,100,100,100,100,100,100,100,100,0,100,1,2,100,100,100,100,100,100,3,4,100,100,100,100,100,100,100,100,100,100,100,100,100,100,100,100,100,100,100,100,100,100,100,100,100,100,100,100,100,100
L1777831665 1 21 iload 5,100,100,100,100,100,100,100,100,100,100,100,100,100,100,100,100,100,100,100,100,100,100,100,100,100,100,0,1,2,100,100,100,100,100,100,3,4,100,100,100,100,100,100,100,100,100,100,100,100,100,100,100,100,100,100,100,100,100,100,100,100,100,100,100,100,100,100
L1777831665 2 46 iaload,100,100,100,100,100,100,100,100,100,100,100,100,100,100,100,100,100,100,100,100,100,100,100,100,100,100,100,0,1,100,100,100,100,100,100,2,3,100,100,100,100,100,100,100,100,100,100,100,100,100,100,100,100,100,100,100,100,100,100,100,100,100,100,100,100,100,100
L1777831665 3 54 istore 8,100,100,100,100,100,100,100,100,100,100,100,100,100,100,100,100,100,100,100,100,100,100,100,100,100,100,100,100,0,100,100,100,100,100,100,1,2,100,100,100,100,100,100,100,100,100,100,100,100,100,100,100,100,100,100,100,100,100,100,100,100,100,100,100,100,100,100
L1865721816 0 21 iload 5,100,100,100,100,100,100,100,100,100,100,100,100,100,2,2,2,2,3,3,3,4,4,4,100,100,2,2,2,2,0,3,1,5,2,2,2,2,100,100,100,100,100,100,100,100,100,100,2,2,2,2,2,2,6,5,5,5,5,5,4,4,4,4,3,4,2,4
L1865721816 1 21 iload 6,100,100,100,100,100,100,100,100,100,100,100,100,100,2,2,2,2,3,3,3,4,4,4,100,100,2,2,2,2,5,0,1,5,2,2,2,2,100,100,100,100,100,100,100,100,100,100,2,2,2,2,2,2,6,5,5,5,5,5,4,4,4,4,3,4,2,4
L1865721816 2 163 if_icmpgt L1471987900,4,2,3,4,4,100,100,2,2,2,2,2,100,1,1,1,1,2,2,2,3,3,3,100,100,1,1,1,1,2,2,0,4,1,1,1,1,100,100,100,100,100,100,100,100,100,100,1,1,1,1,1,1,5,4,4,4,4,4,3,3,3,3,2,3,1,3
L1932213587 0 177 return,100,100,100,100,100,100,100,100,100,100,100,100,100,100,100,100,100,100,100,100,100,100,100,100,100,100,100,100,100,100,100,100,0,100,100,100,100,100,100,100,100,100,100,100,100,100,100,100,100,100,100,100,100,100,100,100,100,100,100,100,100,100,100,100,100,100,100
L1943435117 0 25 aload 1,100,100,100,100,100,100,100,100,100,100,100,100,100,100,100,100,100,100,100,100,100,100,100,100,100,100,100,100,100,100,100,100,100,0,100,100,1,100,100,100,100,100,100,100,100,100,100,100,100,100,100,100,100,100,100,100,100,100,100,100,100,100,100,100,100,100,100
L1943435117 1 21 iload 6,100,100,100,100,100,100,100,100,100,100,100,100,100,100,100,100,100,100,100,100,100,100,100,100,100,100,100,100,100,100,100,100,100,100,0,100,1,100,100,100,100,100,100,100,100,100,100,100,100,100,100,100,100,100,100,100,100,100,100,100,100,100,100,100,100,100,100
L1943435117 2 21 iload 8,100,100,100,100,100,100,100,100,100,100,100,100,100,100,100,100,100,100,100,100,100,100,100,100,100,100,100,100,100,100,100,100,100,100,100,0,1,100,100,100,100,100,100,100,100,100,100,100,100,100,100,100,100,100,100,100,100,100,100,100,100,100,100,100,100,100,100
L1943435117 3 79 iastore,100,100,100,100,100,100,100,100,100,100,100,100,100,100,100,100,100,100,100,100,100,100,100,100,100,100,100,100,100,100,100,100,100,100,100,100,0,100,100,100,100,100,100,100,100,100,100,100,100,100,100,100,100,100,100,100,100,100,100,100,100,100,100,100,100,100,100
L2044708167 0 25 aload 1,100,100,100,100,100,100,100,100,100,100,100,100,100,100,100,100,100,100,100,100,100,100,100,100,100,100,100,100,100,100,100,100,100,100,100,100,100,0,100,100,100,100,100,100,100,1,2,100,100,100,100,100,100,100,100,100,100,100,100,100,100,100,100,100,100,100,100
L2044708167 1 21 iload 2,100,100,100,100,100,100,100,100,100,100,100,100,100,100,100,100,100,100,100,100,100,100,100,100,100,100,100,100,100,100,100,100,100,100,100,100,100,100,0,100,100,100,100,100,1,2,3,100,100,100,100,100,100,100,100,100,100,100,100,100,100,100,100,100,100,100,100
L2044708167 2 21 iload 3,100,100,100,100,100,100,100,100,100,100,100,100,100,100,100,100,100,100,100,100,100,100,100,100,100,100,100,100,100,100,100,100,100,100,100,100,100,100,100,0,100,1,100,2,3,4,5,100,100,100,100,100,100,100,100,100,100,100,100,100,100,100,100,100,100,100,100
L2044708167 3 21 iload 2,100,100,100,100,100,100,100,100,100,100,100,100,100,100,100,100,100,100,100,100,100,100,100,100,100,100,100,100,100,100,100,100,100,100,100,100,100,100,100,100,0,1,100,2,3,4,5,100,100,100,100,100,100,100,100,100,100,100,100,100,100,100,100,100,100,100,100
L2044708167 4 100 isub,100,100,100,100,100,100,100,100,100,100,100,100,100,100,100,100,100,100,100,100,100,100,100,100,100,100,100,100,100,100,100,100,100,100,100,100,100,100,100,100,100,0,100,1,2,3,4,100,100,100,100,100,100,100,100,100,100,100,100,100,100,100,100,100,100,100,100
L2044708167 5 5 iconst_2,100,100,100,100,100,100,100,100,100,100,100,100,100,100,100,100,100,100,100,100,100,100,100,100,100,100,100,100,100,100,100,100,100,100,100,100,100,100,100,100,100,100,0,1,2,3,4,100,100,100,100,100,100,100,100,100,100,100,100,100,100,100,100,100,100,100,100
L2044708167 6 108 idiv,100,100,100,100,100,100,100,100,100,100,100,100,100,100,100,100,100,100,100,100,100,100,100,100,100,100,100,100,100,100,100,100,100,100,100,100,100,100,100,100,100,100,100,0,1,2,3,100,100,100,100,100,100,100,100,100,100,100,100,100,100,100,100,100,100,100,100
L2044708167 7 96 iadd,100,100,100,100,100,100,100,100,100,100,100,100,100,100,100,100,100,100,100,100,100,100,100,100,100,100,100,100,100,100,100,100,100,100,100,100,100,100,100,100,100,100,100,100,0,1,2,100,100,100,100,100,100,100,100,100,100,100,100,100,100,100,100,100,100,100,100
L2044708167 8 46 iaload,100,100,100,2,3,100,100,100,100,100,2,3,100,5,5,5,5,6,6,6,5,7,6,100,100,5,5,5,5,4,4,4,7,5,5,5,5,100,100,100,100,100,100,100,100,0,1,5,5,5,5,5,5,4,7,7,5,7,6,4,7,7,7,6,7,5,4
L2044708167 9 54 istore 7,3,3,3,1,2,100,100,3,3,3,1,2,100,4,4,4,4,5,5,5,4,6,5,100,100,4,4,4,4,3,3,3,6,4,4,4,4,100,100,100,100,100,100,100,100,100,0,4,4,4,4,4,4,3,6,6,4,6,5,3,6,6,6,5,6,4,3
L2076812944 0 25 aload 1,100,100,100,100,100,100,100,100,100,100,100,100,100,100,100,100,100,100,100,100,100,100,100,100,100,100,100,100,100,100,100,100,100,100,100,100,100,100,100,100,100,100,100,100,100,100,100,0,100,100,100,100,1,100,100,100,100,100,100,100,100,100,100,100,100,100,100
L2076812944 1 21 iload 5,100,100,100,100,100,100,100,100,100,100,100,100,100,100,100,100,100,100,100,100,100,100,100,100,100,100,100,100,100,100,100,100,100,100,100,100,100,100,100,100,100,100,100,100,100,100,100,100,0,100,100,100,1,100,100,100,100,100,100,100,100,100,100,100,100,100,100
L2076812944 2 25 aload 1,100,100,100,100,100,100,100,100,100,100,100,100,100,100,100,100,100,100,100,100,100,100,100,100,100,100,100,100,100,100,100,100,100,100,100,100,100,100,100,100,100,100,100,100,100,100,100,100,100,0,100,1,2,100,100,100,100,100,100,100,100,100,100,100,100,100,100
L2076812944 3 21 iload 6,100,100,100,100,100,100,100,100,100,100,100,100,100,100,100,100,100,100,100,100,100,100,100,100,100,100,100,100,100,100,100,100,100,100,100,100,100,100,100,100,100,100,100,100,100,100,100,100,100,100,0,1,2,100,100,100,100,100,100,100,100,100,100,100,100,100,100
L2076812944 4 46 iaload,100,100,100,100,100,100,100,100,100,100,100,100,100,100,100,100,100,100,100,100,100,100,100,100,100,100,100,100,100,100,100,100,100,100,100,100,100,100,100,100,100,100,100,100,100,100,100,100,100,100,100,0,1,100,100,100,100,100,100,100,100,100,100,100,100,100,100
L2076812944 5 79 iastore,100,100,100,100,100,100,100,100,100,100,100,100,100,100,100,100,100,100,100,100,100,100,100,100,100,100,100,100,100,100,100,100,100,100,100,100,100,100,100,100,100,100,100,100,100,100,100,100,100,100,100,100,0,100,100,100,100,100,100,100,100,100,100,100,100,100,100
L2119867878 0 132 iinc 6,100,1,2,4,3,100,100,100,100,100,100,100,100,3,3,3,3,4,4,4,5,5,5,100,100,3,3,3,3,4,1,2,6,3,1,3,2,100,100,100,100,100,100,100,100,100,100,3,3,3,1,2,3,0,6,6,6,6,6,5,5,5,5,4,5,3,5
L466046775 0 25 aload 0,100,100,100,100,100,100,100,100,100,100,100,100,100,100,100,100,100,100,100,100,100,100,100,100,100,100,100,100,100,100,100,100,100,100,100,100,100,100,100,100,100,100,100,100,100,100,100,100,100,100,100,100,100,100,0,100,100,100,1,100,100,100,100,100,100,100,100
L466046775 1 25 aload 1,100,100,100,100,100,100,100,100,100,100,100,100,100,100,100,100,100,100,100,100,100,100,100,100,100,100,100,100,100,100,100,100,100,100,100,100,100,100,100,100,100,100,100,100,100,100,100,100,100,100,100,100,100,100,100,0,100,100,1,100,100,100,100,100,100,100,100
L466046775 2 21 iload 5,100,100,100,100,100,100,100,100,100,100,100,100,100,100,100,100,100,100,100,100,100,100,100,100,100,100,100,100,100,100,100,100,100,100,100,100,100,100,100,100,100,100,100,100,100,100,100,100,100,100,100,100,100,100,100,100,0,100,1,100,100,100,100,100,100,100,100
L466046775 3 21 iload 3,100,100,100,100,100,100,100,100,100,100,100,100,100,100,100,100,100,100,100,100,100,100,100,100,100,100,100,100,100,100,100,100,100,100,100,100,100,100,100,100,100,100,100,100,100,100,100,100,100,100,100,100,100,100,100,100,100,0,1,100,100,100,100,100,100,100,100
L466046775 4 183 invokespecial edu/columbia/psl/cc/Sort quickSort ([III)V,100,100,100,100,100,100,100,100,100,100,100,100,100,100,100,100,100,100,100,100,100,100,100,100,100,100,100,100,100,100,100,100,100,100,100,100,100,100,100,100,100,100,100,100,100,100,100,100,100,100,100,100,100,100,100,100,100,100,0,100,100,100,100,100,100,100,100
L689021860 0 132 iinc 5,100,100,100,100,100,100,100,3,1,2,3,3,100,1,3,2,3,3,3,3,1,4,2,100,100,3,3,3,3,1,4,2,3,3,3,3,3,100,100,100,100,100,100,100,100,100,100,3,3,3,3,3,3,6,3,3,1,3,2,0,4,4,4,4,4,3,4
L802913784 0 25 aload 0,100,100,100,100,100,100,100,100,100,100,100,100,100,100,100,100,100,100,100,100,100,100,100,100,100,100,100,100,100,100,100,100,100,100,100,100,100,100,100,100,100,100,100,100,100,100,100,100,100,100,100,100,100,100,100,100,100,100,100,100,0,100,100,100,1,100,100
L802913784 1 25 aload 1,100,100,100,100,100,100,100,100,100,100,100,100,100,100,100,100,100,100,100,100,100,100,100,100,100,100,100,100,100,100,100,100,100,100,100,100,100,100,100,100,100,100,100,100,100,100,100,100,100,100,100,100,100,100,100,100,100,100,100,100,100,0,100,100,1,100,100
L802913784 2 21 iload 2,100,100,100,100,100,100,100,100,100,100,100,100,100,100,100,100,100,100,100,100,100,100,100,100,100,100,100,100,100,100,100,100,100,100,100,100,100,100,100,100,100,100,100,100,100,100,100,100,100,100,100,100,100,100,100,100,100,100,100,100,100,100,0,100,1,100,100
L802913784 3 21 iload 6,100,100,100,100,100,100,100,100,100,100,100,100,100,100,100,100,100,100,100,100,100,100,100,100,100,100,100,100,100,100,100,100,100,100,100,100,100,100,100,100,100,100,100,100,100,100,100,100,100,100,100,100,100,100,100,100,100,100,100,100,100,100,100,0,1,100,100
L802913784 4 183 invokespecial edu/columbia/psl/cc/Sort quickSort ([III)V,100,100,100,100,100,100,100,100,100,100,100,100,100,100,100,100,100,100,100,100,100,100,100,100,100,100,100,100,100,100,100,100,100,100,100,100,100,100,100,100,100,100,100,100,100,100,100,100,100,100,100,100,100,100,100,100,100,100,100,100,100,100,100,100,0,100,100
L87740549 0 132 iinc 5,100,100,100,100,100,100,100,3,1,2,3,3,100,1,3,2,3,3,3,3,4,4,4,100,100,3,1,2,3,1,4,2,5,3,3,3,3,100,100,100,100,100,100,100,100,100,100,3,1,3,3,3,2,6,5,5,5,5,5,4,4,4,4,4,4,0,4
L959260223 0 167 goto L1126829932,1,1,1,1,1,100,100,100,100,100,100,100,100,3,3,3,3,4,4,4,5,5,5,100,100,3,3,3,3,2,2,2,6,3,3,3,3,100,100,100,100,100,100,100,100,100,100,3,3,3,3,3,3,2,6,6,6,6,6,5,5,5,5,4,5,3,0
