MIB premain test
edu/columbia/psl/cc/premain/MIBDriver extends java/lang/Object{
}
com/google/gson/reflect/TypeToken extends java/lang/Object{
}
edu/columbia/psl/cc/premain/MIBDriver$1 extends com/google/gson/reflect/TypeToken{
}
edu/columbia/psl/cc/util/Analyzer extends java/lang/Object{
}
edu/columbia/psl/cc/premain/MIBDriver$2 extends com/google/gson/reflect/TypeToken{
}
edu/columbia/psl/cc/util/GsonManager extends java/lang/Object{
}
edu/columbia/psl/cc/config/MIBConfiguration extends java/lang/Object{
}
edu/columbia/psl/cc/test/TemplateMethod extends edu/columbia/psl/cc/test/TemplateParent{
Annotation: Ledu/columbia/psl/cc/annot/analyzeClass;
Template annotated: Ledu/columbia/psl/cc/annot/extractTemplate;
Method name: fieldTest
Method Stack Recorder name: edu/columbia/psl/cc/util/MethodStackRecorder
Template annotated: Ledu/columbia/psl/cc/annot/extractTemplate;
Method name: dummyFor
Method Stack Recorder name: edu/columbia/psl/cc/util/MethodStackRecorder
Template annotated: Ledu/columbia/psl/cc/annot/extractTemplate;
Method name: add
Method Stack Recorder name: edu/columbia/psl/cc/util/MethodStackRecorder
Template annotated: Ledu/columbia/psl/cc/annot/extractTemplate;
Method name: addOutside
Method Stack Recorder name: edu/columbia/psl/cc/util/MethodStackRecorder
}
edu/columbia/psl/cc/test/TemplateParent extends java/lang/Object{
}
Confirm class: class edu.columbia.psl.cc.test.TemplateMethod
edu/columbia/psl/cc/util/MethodStackRecorder$1 extends com/google/gson/reflect/TypeToken{
}
Handling now: 25 0
Check lastInst: null
Stack push: edu.columbia.psl.cc.test.TemplateMethod:addOutside:(II):I 0 25 aload 0
[edu.columbia.psl.cc.test.TemplateMethod:addOutside:(II):I 0 25 aload 0]
Handling now: 21 1
Check lastInst: edu.columbia.psl.cc.test.TemplateMethod:addOutside:(II):I 0 25 aload 0
Stack push: edu.columbia.psl.cc.test.TemplateMethod:addOutside:(II):I 1 21 iload 1
[edu.columbia.psl.cc.test.TemplateMethod:addOutside:(II):I 0 25 aload 0, edu.columbia.psl.cc.test.TemplateMethod:addOutside:(II):I 1 21 iload 1]
Handling now: 21 2
Check lastInst: edu.columbia.psl.cc.test.TemplateMethod:addOutside:(II):I 1 21 iload 1
Stack push: edu.columbia.psl.cc.test.TemplateMethod:addOutside:(II):I 2 21 iload 2
[edu.columbia.psl.cc.test.TemplateMethod:addOutside:(II):I 0 25 aload 0, edu.columbia.psl.cc.test.TemplateMethod:addOutside:(II):I 1 21 iload 1, edu.columbia.psl.cc.test.TemplateMethod:addOutside:(II):I 2 21 iload 2]
Method full inst: edu.columbia.psl.cc.test.TemplateMethod:addOutside:(II):I 3 182 invokevirtual edu.columbia.psl.cc.test.TemplateMethod:add:(II):I
Arg size: 3
Stack push: edu.columbia.psl.cc.test.TemplateMethod:addOutside:(II):I 3 182 invokevirtual edu.columbia.psl.cc.test.TemplateMethod:add:(II):I
[edu.columbia.psl.cc.test.TemplateMethod:addOutside:(II):I 3 182 invokevirtual edu.columbia.psl.cc.test.TemplateMethod:add:(II):I]
Handling now: 21 1
Check lastInst: null
Stack push: edu.columbia.psl.cc.test.TemplateMethod:add:(II):I 0 21 iload 1
[edu.columbia.psl.cc.test.TemplateMethod:add:(II):I 0 21 iload 1]
Handling now: 21 2
Check lastInst: edu.columbia.psl.cc.test.TemplateMethod:add:(II):I 0 21 iload 1
Stack push: edu.columbia.psl.cc.test.TemplateMethod:add:(II):I 1 21 iload 2
[edu.columbia.psl.cc.test.TemplateMethod:add:(II):I 0 21 iload 1, edu.columbia.psl.cc.test.TemplateMethod:add:(II):I 1 21 iload 2]
Handling now: 96 -1
Check lastInst: edu.columbia.psl.cc.test.TemplateMethod:add:(II):I 1 21 iload 2
Stack push: edu.columbia.psl.cc.test.TemplateMethod:add:(II):I 2 96 iadd 
[edu.columbia.psl.cc.test.TemplateMethod:add:(II):I 2 96 iadd ]
Handling now: 172 -1
Check lastInst: edu.columbia.psl.cc.test.TemplateMethod:add:(II):I 2 96 iadd 
Stack push: edu.columbia.psl.cc.test.TemplateMethod:add:(II):I 3 172 ireturn 
[]
edu/columbia/psl/cc/pojo/GraphTemplate extends java/lang/Object{
}
Instruction dependency:
Parent: edu.columbia.psl.cc.test.TemplateMethod:add:(II):I 0 21 iload 1
  Child: edu.columbia.psl.cc.test.TemplateMethod:add:(II):I 2 96 iadd  Freq: 1.0
Parent: edu.columbia.psl.cc.test.TemplateMethod:add:(II):I 1 21 iload 2
  Child: edu.columbia.psl.cc.test.TemplateMethod:add:(II):I 2 96 iadd  Freq: 1.0
Parent: edu.columbia.psl.cc.test.TemplateMethod:add:(II):I 2 96 iadd 
  Child: edu.columbia.psl.cc.test.TemplateMethod:add:(II):I 3 172 ireturn  Freq: 1.0
Parent: edu.columbia.psl.cc.test.TemplateMethod:add:(II):I 3 172 ireturn 
Total dependency count: 3
com/google/gson/internal/ConstructorConstructor$8 extends java/lang/Object{
}
com/google/gson/internal/LinkedTreeMap extends java/util/AbstractMap{
}
com/google/gson/internal/LinkedTreeMap$1 extends java/lang/Object{
}
com/google/gson/internal/LinkedTreeMap$Node extends java/lang/Object{
}
com/google/gson/internal/LinkedTreeMap$EntrySet extends java/util/AbstractSet{
}
com/google/gson/internal/LinkedTreeMap$EntrySet$1 extends com/google/gson/internal/LinkedTreeMap$LinkedTreeMapIterator{
}
com/google/gson/internal/LinkedTreeMap$LinkedTreeMapIterator extends java/lang/Object{
}
Handling now: 54 4
Check lastInst: edu.columbia.psl.cc.test.TemplateMethod:addOutside:(II):I 3 182 invokevirtual edu.columbia.psl.cc.test.TemplateMethod:add:(II):I
Update data dep
Stack push: edu.columbia.psl.cc.test.TemplateMethod:addOutside:(II):I 4 54 istore 4
[]
Handling now: 21 4
Check lastInst: null
Stack push: edu.columbia.psl.cc.test.TemplateMethod:addOutside:(II):I 5 21 iload 4
[edu.columbia.psl.cc.test.TemplateMethod:addOutside:(II):I 5 21 iload 4]
Handling now: 172 -1
Check lastInst: edu.columbia.psl.cc.test.TemplateMethod:addOutside:(II):I 5 21 iload 4
Stack push: edu.columbia.psl.cc.test.TemplateMethod:addOutside:(II):I 6 172 ireturn 
[]
Instruction dependency:
Parent: edu.columbia.psl.cc.test.TemplateMethod:addOutside:(II):I 0 25 aload 0
  Child: edu.columbia.psl.cc.test.TemplateMethod:addOutside:(II):I 3 182 invokevirtual edu.columbia.psl.cc.test.TemplateMethod:add:(II):I Freq: 1.0
Parent: edu.columbia.psl.cc.test.TemplateMethod:addOutside:(II):I 1 21 iload 1
  Child: edu.columbia.psl.cc.test.TemplateMethod:addOutside:(II):I 3 182 invokevirtual edu.columbia.psl.cc.test.TemplateMethod:add:(II):I Freq: 1.0
Parent: edu.columbia.psl.cc.test.TemplateMethod:addOutside:(II):I 2 21 iload 2
  Child: edu.columbia.psl.cc.test.TemplateMethod:addOutside:(II):I 3 182 invokevirtual edu.columbia.psl.cc.test.TemplateMethod:add:(II):I Freq: 1.0
Parent: edu.columbia.psl.cc.test.TemplateMethod:addOutside:(II):I 3 182 invokevirtual edu.columbia.psl.cc.test.TemplateMethod:add:(II):I
  Child: edu.columbia.psl.cc.test.TemplateMethod:addOutside:(II):I 4 54 istore 4 Freq: 1.0
Parent: edu.columbia.psl.cc.test.TemplateMethod:addOutside:(II):I 4 54 istore 4
  Child: edu.columbia.psl.cc.test.TemplateMethod:addOutside:(II):I 5 21 iload 4 Freq: 1.0
Parent: edu.columbia.psl.cc.test.TemplateMethod:addOutside:(II):I 5 21 iload 4
  Child: edu.columbia.psl.cc.test.TemplateMethod:addOutside:(II):I 6 172 ireturn  Freq: 1.0
Parent: edu.columbia.psl.cc.test.TemplateMethod:addOutside:(II):I 6 172 ireturn 
Total dependency count: 6
TempalteMethod: 8
Handling now: 25 0
Check lastInst: null
Stack push: edu.columbia.psl.cc.test.TemplateMethod:fieldTest:():I 0 25 aload 0
[edu.columbia.psl.cc.test.TemplateMethod:fieldTest:():I 0 25 aload 0]
Handling now: 8 -1
Check lastInst: edu.columbia.psl.cc.test.TemplateMethod:fieldTest:():I 0 25 aload 0
Stack push: edu.columbia.psl.cc.test.TemplateMethod:fieldTest:():I 1 8 iconst_5 
[edu.columbia.psl.cc.test.TemplateMethod:fieldTest:():I 0 25 aload 0, edu.columbia.psl.cc.test.TemplateMethod:fieldTest:():I 1 8 iconst_5 ]
Stack push: edu.columbia.psl.cc.test.TemplateMethod:fieldTest:():I 2 181 putfield edu/columbia/psl/cc/test/TemplateMethod.iVar.I
[]
Handling now: 25 0
Check lastInst: null
Stack push: edu.columbia.psl.cc.test.TemplateMethod:fieldTest:():I 3 25 aload 0
[edu.columbia.psl.cc.test.TemplateMethod:fieldTest:():I 3 25 aload 0]
Stack push: edu.columbia.psl.cc.test.TemplateMethod:fieldTest:():I 4 180 getfield edu/columbia/psl/cc/test/TemplateMethod.iVar.I
[edu.columbia.psl.cc.test.TemplateMethod:fieldTest:():I 4 180 getfield edu/columbia/psl/cc/test/TemplateMethod.iVar.I]
Stack push: edu.columbia.psl.cc.test.TemplateMethod:fieldTest:():I 5 178 getstatic edu/columbia/psl/cc/test/TemplateMethod.sVar.I
[edu.columbia.psl.cc.test.TemplateMethod:fieldTest:():I 4 180 getfield edu/columbia/psl/cc/test/TemplateMethod.iVar.I, edu.columbia.psl.cc.test.TemplateMethod:fieldTest:():I 5 178 getstatic edu/columbia/psl/cc/test/TemplateMethod.sVar.I]
Handling now: 96 -1
Check lastInst: edu.columbia.psl.cc.test.TemplateMethod:fieldTest:():I 5 178 getstatic edu/columbia/psl/cc/test/TemplateMethod.sVar.I
Stack push: edu.columbia.psl.cc.test.TemplateMethod:fieldTest:():I 6 96 iadd 
[edu.columbia.psl.cc.test.TemplateMethod:fieldTest:():I 6 96 iadd ]
Handling now: 54 2
Check lastInst: edu.columbia.psl.cc.test.TemplateMethod:fieldTest:():I 6 96 iadd 
Update data dep
Stack push: edu.columbia.psl.cc.test.TemplateMethod:fieldTest:():I 7 54 istore 2
[]
Handling now: 25 0
Check lastInst: null
Stack push: edu.columbia.psl.cc.test.TemplateMethod:fieldTest:():I 8 25 aload 0
[edu.columbia.psl.cc.test.TemplateMethod:fieldTest:():I 8 25 aload 0]
Stack push: edu.columbia.psl.cc.test.TemplateMethod:fieldTest:():I 9 180 getfield edu/columbia/psl/cc/test/TemplateMethod.iVar.I
[edu.columbia.psl.cc.test.TemplateMethod:fieldTest:():I 9 180 getfield edu/columbia/psl/cc/test/TemplateMethod.iVar.I]
Handling now: 16 7
Check lastInst: edu.columbia.psl.cc.test.TemplateMethod:fieldTest:():I 9 180 getfield edu/columbia/psl/cc/test/TemplateMethod.iVar.I
Stack push: edu.columbia.psl.cc.test.TemplateMethod:fieldTest:():I 10 16 bipush 7
[edu.columbia.psl.cc.test.TemplateMethod:fieldTest:():I 9 180 getfield edu/columbia/psl/cc/test/TemplateMethod.iVar.I, edu.columbia.psl.cc.test.TemplateMethod:fieldTest:():I 10 16 bipush 7]
Handling now: 96 -1
Check lastInst: edu.columbia.psl.cc.test.TemplateMethod:fieldTest:():I 10 16 bipush 7
Stack push: edu.columbia.psl.cc.test.TemplateMethod:fieldTest:():I 11 96 iadd 
[edu.columbia.psl.cc.test.TemplateMethod:fieldTest:():I 11 96 iadd ]
Handling now: 54 3
Check lastInst: edu.columbia.psl.cc.test.TemplateMethod:fieldTest:():I 11 96 iadd 
Update data dep
Stack push: edu.columbia.psl.cc.test.TemplateMethod:fieldTest:():I 12 54 istore 3
[]
Handling now: 21 2
Check lastInst: null
Stack push: edu.columbia.psl.cc.test.TemplateMethod:fieldTest:():I 13 21 iload 2
[edu.columbia.psl.cc.test.TemplateMethod:fieldTest:():I 13 21 iload 2]
Handling now: 172 -1
Check lastInst: edu.columbia.psl.cc.test.TemplateMethod:fieldTest:():I 13 21 iload 2
Stack push: edu.columbia.psl.cc.test.TemplateMethod:fieldTest:():I 14 172 ireturn 
[]
Instruction dependency:
Parent: edu.columbia.psl.cc.test.TemplateMethod:fieldTest:():I 0 25 aload 0
  Child: edu.columbia.psl.cc.test.TemplateMethod:fieldTest:():I 2 181 putfield edu/columbia/psl/cc/test/TemplateMethod.iVar.I Freq: 1.0
Parent: edu.columbia.psl.cc.test.TemplateMethod:fieldTest:():I 1 8 iconst_5 
  Child: edu.columbia.psl.cc.test.TemplateMethod:fieldTest:():I 2 181 putfield edu/columbia/psl/cc/test/TemplateMethod.iVar.I Freq: 1.0
Parent: edu.columbia.psl.cc.test.TemplateMethod:fieldTest:():I 2 181 putfield edu/columbia/psl/cc/test/TemplateMethod.iVar.I
  Child: edu.columbia.psl.cc.test.TemplateMethod:fieldTest:():I 4 180 getfield edu/columbia/psl/cc/test/TemplateMethod.iVar.I Freq: 1.0
  Child: edu.columbia.psl.cc.test.TemplateMethod:fieldTest:():I 9 180 getfield edu/columbia/psl/cc/test/TemplateMethod.iVar.I Freq: 1.0
Parent: edu.columbia.psl.cc.test.TemplateMethod:fieldTest:():I 3 25 aload 0
  Child: edu.columbia.psl.cc.test.TemplateMethod:fieldTest:():I 4 180 getfield edu/columbia/psl/cc/test/TemplateMethod.iVar.I Freq: 1.0
Parent: edu.columbia.psl.cc.test.TemplateMethod:fieldTest:():I 4 180 getfield edu/columbia/psl/cc/test/TemplateMethod.iVar.I
  Child: edu.columbia.psl.cc.test.TemplateMethod:fieldTest:():I 6 96 iadd  Freq: 1.0
Parent: edu.columbia.psl.cc.test.TemplateMethod:fieldTest:():I 5 178 getstatic edu/columbia/psl/cc/test/TemplateMethod.sVar.I
  Child: edu.columbia.psl.cc.test.TemplateMethod:fieldTest:():I 6 96 iadd  Freq: 1.0
Parent: edu.columbia.psl.cc.test.TemplateMethod:fieldTest:():I 6 96 iadd 
  Child: edu.columbia.psl.cc.test.TemplateMethod:fieldTest:():I 7 54 istore 2 Freq: 1.0
Parent: edu.columbia.psl.cc.test.TemplateMethod:fieldTest:():I 7 54 istore 2
  Child: edu.columbia.psl.cc.test.TemplateMethod:fieldTest:():I 13 21 iload 2 Freq: 1.0
Parent: edu.columbia.psl.cc.test.TemplateMethod:fieldTest:():I 8 25 aload 0
  Child: edu.columbia.psl.cc.test.TemplateMethod:fieldTest:():I 9 180 getfield edu/columbia/psl/cc/test/TemplateMethod.iVar.I Freq: 1.0
Parent: edu.columbia.psl.cc.test.TemplateMethod:fieldTest:():I 9 180 getfield edu/columbia/psl/cc/test/TemplateMethod.iVar.I
  Child: edu.columbia.psl.cc.test.TemplateMethod:fieldTest:():I 11 96 iadd  Freq: 1.0
Parent: edu.columbia.psl.cc.test.TemplateMethod:fieldTest:():I 10 16 bipush 7
  Child: edu.columbia.psl.cc.test.TemplateMethod:fieldTest:():I 11 96 iadd  Freq: 1.0
Parent: edu.columbia.psl.cc.test.TemplateMethod:fieldTest:():I 11 96 iadd 
  Child: edu.columbia.psl.cc.test.TemplateMethod:fieldTest:():I 12 54 istore 3 Freq: 1.0
Parent: edu.columbia.psl.cc.test.TemplateMethod:fieldTest:():I 12 54 istore 3
Parent: edu.columbia.psl.cc.test.TemplateMethod:fieldTest:():I 13 21 iload 2
  Child: edu.columbia.psl.cc.test.TemplateMethod:fieldTest:():I 14 172 ireturn  Freq: 1.0
Parent: edu.columbia.psl.cc.test.TemplateMethod:fieldTest:():I 14 172 ireturn 
Total dependency count: 14
5
edu/columbia/psl/cc/util/TemplateLoader extends java/lang/Object{
}
edu/columbia/psl/cc/util/TemplateLoader$1 extends java/lang/Object{
}
com/google/gson/internal/JsonReaderInternalAccess extends java/lang/Object{
}
com/google/gson/stream/JsonReader$1 extends com/google/gson/internal/JsonReaderInternalAccess{
}
com/google/gson/stream/JsonToken extends java/lang/Enum{
}
com/google/gson/internal/bind/TypeAdapters$32 extends java/lang/Object{
}
Dynamic Graph Analysis
edu/columbia/psl/cc/util/DynamicGraphAnalyzer extends java/lang/Object{
}
edu/columbia/psl/cc/analysis/MIBSimilarity extends java/lang/Object{
}
edu/columbia/psl/cc/analysis/ShortestPathKernel extends java/lang/Object{
}
edu/columbia/psl/cc/pojo/CostObj extends java/lang/Object{
}
edu/columbia/psl/cc/util/GraphUtil extends java/lang/Object{
}
edu/columbia/psl/cc/util/GraphUtil$1 extends com/google/gson/reflect/TypeToken{
}
org/apache/commons/math3/util/Precision extends java/lang/Object{
}
org/apache/commons/math3/exception/MathArithmeticException extends java/lang/ArithmeticException{
}
org/apache/commons/math3/exception/util/ExceptionContextProvider extends java/lang/Object{
}
org/apache/commons/math3/exception/util/Localizable extends java/lang/Object{
}
org/apache/commons/math3/exception/MathIllegalArgumentException extends java/lang/IllegalArgumentException{
}
Check cost table
Check cost table
Check cost table
Static Analysis
edu/columbia/psl/cc/util/StaticBytecodeCatAnalyzer extends java/lang/Object{
}
edu/columbia/psl/cc/util/StaticBytecodeCatAnalyzer$2 extends com/google/gson/reflect/TypeToken{
}
edu/columbia/psl/cc/analysis/LevenshteinDistance extends java/lang/Object{
}
com/apple/java/Usage$3 extends java/lang/Object{
}
com/apple/java/Application extends java/lang/Object{
}
com/apple/java/Application$1 extends java/lang/Object{
}
