{
  "lastSecondInst": "L67 0 21 iload 4",
  "invokeMethodLookup": {
    "edu_columbia_psl_cc_test_TemplateMethod~add~II~I": [
      "L8 0 25 aload 0",
      "L8 1 21 iload 1",
      "L8 2 21 iload 2"
    ]
  },
  "dataGraph": {
    "L67 0 21 iload 4": [
      "L67 1 172 ireturn"
    ],
    "L8 0 25 aload 0": [
      "L8 3 182 invokevirtual edu/columbia/psl/cc/test/TemplateMethod add (II)I"
    ],
    "L8 1 21 iload 1": [
      "L8 3 182 invokevirtual edu/columbia/psl/cc/test/TemplateMethod add (II)I"
    ],
    "L8 2 21 iload 2": [
      "L8 3 182 invokevirtual edu/columbia/psl/cc/test/TemplateMethod add (II)I"
    ],
    "L8 3 182 invokevirtual edu/columbia/psl/cc/test/TemplateMethod add (II)I": [
      "L8 4 54 istore 4"
    ],
    "L8 4 54 istore 4": [
      "L67 0 21 iload 4"
    ]
  },
  "controlGraph": {}
}